{"nodes": [{"id": "workflows_release_rize_backend_release", "label": "Backend Release Workflow (GoReleaser on v* tags)", "file_type": "code", "source_file": "rize-backend/.github/workflows/release.yml", "source_location": null, "source_url": null, "captured_at": null, "author": null, "contributor": null}], "edges": [{"source": "workflows_release_rize_backend_release", "target": "rize_backend_goreleaser_config", "relation": "references", "confidence": "INFERRED", "confidence_score": 0.95, "source_file": "rize-backend/.github/workflows/release.yml", "source_location": null, "weight": 1.0}], "hyperedges": []}